[
  {
    "code": "YHNOWTOENJOY",
    "reward": "前瞻直播专属奖励",
    "rewardEn": "Livestream Exclusive Rewards",
    "status": "active",
    "expiresAt": "2026-05-23",
    "source": "livestream",
    "region": "cn",
    "revealedAt": "2026-04-18"
  },
  {
    "code": "YHNANALLYGO",
    "reward": "前瞻直播专属奖励",
    "rewardEn": "Livestream Exclusive Rewards",
    "status": "active",
    "expiresAt": "2026-05-23",
    "source": "livestream",
    "region": "cn",
    "revealedAt": "2026-04-18"
  },
  {
    "code": "YHOB0423",
    "reward": "前瞻直播专属奖励",
    "rewardEn": "Livestream Exclusive Rewards",
    "status": "active",
    "expiresAt": "2026-05-23",
    "source": "livestream",
    "region": "cn",
    "revealedAt": "2026-04-18"
  },
  {
    "code": "NTENOWTOENJOY",
    "reward": "前瞻直播专属奖励",
    "rewardEn": "Livestream Exclusive Rewards",
    "status": "active",
    "expiresAt": "2026-05-29",
    "source": "livestream",
    "region": "global",
    "revealedAt": "2026-04-18"
  },
  {
    "code": "NTENANALLYGO",
    "reward": "前瞻直播专属奖励",
    "rewardEn": "Livestream Exclusive Rewards",
    "status": "active",
    "expiresAt": "2026-05-29",
    "source": "livestream",
    "region": "global",
    "revealedAt": "2026-04-18"
  },
  {
    "code": "NTE0429",
    "reward": "前瞻直播专属奖励",
    "rewardEn": "Livestream Exclusive Rewards",
    "status": "active",
    "expiresAt": "2026-05-29",
    "source": "livestream",
    "region": "global",
    "revealedAt": "2026-04-18"
  }
]
